{"success":true,"otps":[{"country":"Benin","flag":"🇧🇯","id":"2026-07-10 07:31:52_2290148970050_&lt;#&gt; Your WhatsApp Business account is being ","masked_number":"22••0050","message":"&lt;#&gt; Your WhatsApp Business account is being registered on a new device\\n\\nDo not share this code with anyone\\nYour WhatsApp Business code: 961-366\\nrJbA/XP1K+V","number":"2290148970050","otp":"961366","panel":"Zone Panel","sender":"WhatsApp","time":"2026-07-10 07:31:52","timestamp":"2026-07-10T07:31:55.569999"}]}