{"success":true,"otps":[{"country":"Benin","flag":"🇧🇯","id":"2026-05-23 21:26:03_2290148461270_&lt;#&gt; Akun WhatsApp Business Anda sedang didaf","masked_number":"22••1270","message":"&lt;#&gt; Akun WhatsApp Business Anda sedang didaftarkan di perangkat baru\\n\\nJangan bagikan kode dengan siapa pun\\nKode WhatsApp Business Anda: 692-692\\nrJbA/XP1K+V","number":"2290148461270","otp":"692692","panel":"Zone Panel","sender":"WhatsApp","time":"2026-05-23 21:26:03","timestamp":"2026-05-23T21:26:04.453894"}]}