{"success":true,"otps":[{"country":"Congo, The Democratic Republic of the","flag":"🇨🇩","id":"2026-05-24 04:10:56_243854563661_&lt;#&gt; Akun WhatsApp Business Anda sedang didaf","masked_number":"24••3661","message":"&lt;#&gt; Akun WhatsApp Business Anda sedang didaftarkan di perangkat baru\\n\\nJangan bagikan kode dengan siapa pun\\nKode WhatsApp Business Anda: 206-870\\nrJbA/XP1K+V","number":"243854563661","otp":"206870","panel":"Zone Panel","sender":"WhatsApp","time":"2026-05-24 04:10:56","timestamp":"2026-05-24T04:10:57.950365"}]}