{"success":true,"otps":[{"country":"Venezuela, Bolivarian Republic of","flag":"🇻🇪","id":"2026-05-05 15:09:30_584163107422_&lt;#&gt; Akun WhatsApp Business Anda sedang didaf","masked_number":"58••7422","message":"&lt;#&gt; Akun WhatsApp Business Anda sedang didaftarkan di perangkat baru\\n\\nJangan bagikan kode dengan siapa pun\\nKode WhatsApp Business Anda: 740-615\\nrJbA/XP1K+V","number":"584163107422","otp":"740615","panel":"Zone Panel","sender":"WhatsApp","time":"2026-05-05 15:09:30","timestamp":"2026-05-05T15:09:33.316099"}]}