{"success":true,"otps":[{"country":"Venezuela, Bolivarian Republic of","flag":"🇻🇪","id":"2026-03-26 16:03:44_584167080959_&lt;#&gt; Tu cuenta de WhatsApp esta siendo regist","masked_number":"58••0959","message":"&lt;#&gt; Tu cuenta de WhatsApp esta siendo registrada en un dispositivo nuevo\\n\\nNo compartas el codigo con nadie\\nTu codigo de WhatsApp es: 355-948\\n4sgLq1p5sV6","number":"584167080959","otp":"355948","panel":"Zone Panel","sender":"Whatsapp","time":"2026-03-26 16:03:44","timestamp":"2026-03-26T16:03:47.396696"}]}