{"success":true,"otps":[{"country":"Venezuela, Bolivarian Republic of","flag":"🇻🇪","id":"2026-04-22 11:16:47_584163696430_&lt;#&gt; Akun WhatsApp Anda sedang didaftarkan di","masked_number":"58••6430","message":"&lt;#&gt; Akun WhatsApp Anda sedang didaftarkan di perangkat baru\\n\\nJangan bagikan kode dengan siapa pun\\nKode WhatsApp Anda: 812-185\\n4sgLq1p5sV6","number":"584163696430","otp":"812185","panel":"Zone Panel","sender":"WhatsApp","time":"2026-04-22 11:16:47","timestamp":"2026-04-22T11:16:48.141914"}]}