{"success":true,"otps":[{"country":"Venezuela, Bolivarian Republic of","flag":"🇻🇪","id":"2026-04-21 22:33:54_584164023164_&lt;#&gt; Kode WhatsApp Business: 633-451\\nJangan ","masked_number":"58••3164","message":"&lt;#&gt; Kode WhatsApp Business: 633-451\\nJangan bagikan kode ini dengan orang lain\\nrJbA/XP1K+V","number":"584164023164","otp":"633451","panel":"Zone Panel","sender":"WhatsApp","time":"2026-04-21 22:33:54","timestamp":"2026-04-21T22:33:55.562016"},{"country":"Venezuela, Bolivarian Republic of","flag":"🇻🇪","id":"2026-04-21 22:33:32_584164023164_&lt;#&gt; Akun WhatsApp Business Anda sedang didaf","masked_number":"58••3164","message":"&lt;#&gt; Akun WhatsApp Business Anda sedang didaftarkan di perangkat baru\\n\\nJangan bagikan kode dengan siapa pun\\nKode WhatsApp Business Anda: 814-371\\nrJbA/XP1K+V","number":"584164023164","otp":"814371","panel":"Zone Panel","sender":"WhatsApp","time":"2026-04-21 22:33:32","timestamp":"2026-04-21T22:33:35.594028"}]}