{"success":true,"otps":[{"country":"Venezuela, Bolivarian Republic of","flag":"🇻🇪","id":"2026-03-26 15:01:50_584162597867_[rednote]Your verification code is 192665, for ver","masked_number":"58••7867","message":"[rednote]Your verification code is 192665, for verification code login, please verify within 5 mins. Do not share the verification code to others.","number":"584162597867","otp":"192665","panel":"Zone Panel","sender":"rednote","time":"2026-03-26 15:01:50","timestamp":"2026-03-26T15:01:51.101727"}]}