{"success":true,"otps":[{"country":"Venezuela, Bolivarian Republic of","flag":"🇻🇪","id":"2026-04-20 04:22:39_584164985467_&lt;#&gt; Akun WhatsApp Business Anda sedang didaf","masked_number":"58••5467","message":"&lt;#&gt; Akun WhatsApp Business Anda sedang didaftarkan di perangkat baru\\n\\nJangan bagikan kode dengan siapa pun\\nKode WhatsApp Business Anda: 824-445\\nrJbA/XP1K+V","number":"584164985467","otp":"824445","panel":"Zone Panel","sender":"WhatsApp","time":"2026-04-20 04:22:39","timestamp":"2026-04-20T04:22:42.737862"}]}