{"success":true,"otps":[{"country":"Venezuela, Bolivarian Republic of","flag":"🇻🇪","id":"2026-04-16 08:38:24_584164171094_&lt;#&gt; Kode WhatsApp: 486-173\\nJangan bagikan k","masked_number":"58••1094","message":"&lt;#&gt; Kode WhatsApp: 486-173\\nJangan bagikan kode ini dengan orang lain\\n4sgLq1p5sV6","number":"584164171094","otp":"486173","panel":"Zone Panel","sender":"16579991951","time":"2026-04-16 08:38:24","timestamp":"2026-04-16T08:38:25.039227"},{"country":"Venezuela, Bolivarian Republic of","flag":"🇻🇪","id":"2026-04-16 08:12:38_584164171094_&lt;#&gt; Akun WhatsApp Anda sedang didaftarkan di","masked_number":"58••1094","message":"&lt;#&gt; Akun WhatsApp Anda sedang didaftarkan di perangkat baru\\n\\nJangan bagikan kode dengan siapa pun\\nKode WhatsApp Anda: 622-621\\n4sgLq1p5sV6","number":"584164171094","otp":"622621","panel":"Zone Panel","sender":"16579991951","time":"2026-04-16 08:12:38","timestamp":"2026-04-16T08:12:38.904757"}]}