{"success":true,"otps":[{"country":"Venezuela, Bolivarian Republic of","flag":"🇻🇪","id":"2026-04-24 14:02:06_584161594797_&lt;#&gt; Akun WhatsApp Business Anda sedang didaf","masked_number":"58••4797","message":"&lt;#&gt; Akun WhatsApp Business Anda sedang didaftarkan di perangkat baru\\n\\nJangan bagikan kode dengan siapa pun\\nKode WhatsApp Business Anda: 490-916\\nrJbA/XP1K+V","number":"584161594797","otp":"490916","panel":"Zone Panel","sender":"WhatsApp","time":"2026-04-24 14:02:06","timestamp":"2026-04-24T14:02:08.857411"}]}