{"success":true,"otps":[{"country":"Venezuela, Bolivarian Republic of","flag":"🇻🇪","id":"2026-04-22 15:31:56_584168729664_&lt;#&gt; Akun WhatsApp Anda sedang didaftarkan di","masked_number":"58••9664","message":"&lt;#&gt; Akun WhatsApp Anda sedang didaftarkan di perangkat baru\\n\\nJangan bagikan kode dengan siapa pun\\nKode WhatsApp Anda: 703-254\\n4sgLq1p5sV6","number":"584168729664","otp":"703254","panel":"Zone Panel","sender":"WhatsApp","time":"2026-04-22 15:31:56","timestamp":"2026-04-22T15:31:58.876449"}]}