{"success":true,"otps":[{"country":"Venezuela, Bolivarian Republic of","flag":"🇻🇪","id":"2026-04-27 21:31:23_584164798550_&lt;#&gt; Your WhatsApp code: 873-866\\nDon\\&#039;t","masked_number":"58••8550","message":"&lt;#&gt; Your WhatsApp code: 873-866\\nDon\\&#039;t share this code with others\\n4sgLq1p5sV6","number":"584164798550","otp":"873866","panel":"Zone Panel","sender":"WhatsApp","time":"2026-04-27 21:31:23","timestamp":"2026-04-27T21:31:24.094253"},{"country":"Venezuela, Bolivarian Republic of","flag":"🇻🇪","id":"2026-04-27 21:30:48_584164798550_&lt;#&gt; Your WhatsApp account is being registere","masked_number":"58••8550","message":"&lt;#&gt; Your WhatsApp account is being registered on a new device\\n\\nDo not share this code with anyone\\nYour WhatsApp code: 710-362\\n4sgLq1p5sV6","number":"584164798550","otp":"710362","panel":"Zone Panel","sender":"WhatsApp","time":"2026-04-27 21:30:48","timestamp":"2026-04-27T21:30:50.797127"}]}