{"success":true,"otps":[{"country":"Venezuela, Bolivarian Republic of","flag":"🇻🇪","id":"2026-05-06 18:50:44_584163184357_396681 is your Instagram code. Don\\&#039;t share i","masked_number":"58••4357","message":"396681 is your Instagram code. Don\\&#039;t share it. #ig","number":"584163184357","otp":"396681","panel":"Zone Panel","sender":"12567480245","time":"2026-05-06 18:50:44","timestamp":"2026-05-06T18:50:47.052996"},{"country":"Venezuela, Bolivarian Republic of","flag":"🇻🇪","id":"2026-05-06 18:40:53_584163184357_602927 is your Instagram code. Don\\&#039;t share i","masked_number":"58••4357","message":"602927 is your Instagram code. Don\\&#039;t share it. #ig","number":"584163184357","otp":"602927","panel":"Zone Panel","sender":"12567480245","time":"2026-05-06 18:40:53","timestamp":"2026-05-06T18:40:56.703915"},{"country":"Venezuela, Bolivarian Republic of","flag":"🇻🇪","id":"2026-05-06 18:36:55_584163184357_602927 is your Instagram code. Don\\&#039;t share i","masked_number":"58••4357","message":"602927 is your Instagram code. Don\\&#039;t share it. #ig","number":"584163184357","otp":"602927","panel":"Zone Panel","sender":"12567480245","time":"2026-05-06 18:36:55","timestamp":"2026-05-06T18:36:56.319695"}]}