{"success":true,"otps":[{"country":"Venezuela, Bolivarian Republic of","flag":"🇻🇪","id":"2026-04-16 16:26:43_584166609161_Tu cuenta de WhatsApp esta siendo registrada en un","masked_number":"58••9161","message":"Tu cuenta de WhatsApp esta siendo registrada en un dispositivo nuevo\\n\\nNo compartas el codigo con nadie\\nTu codigo de WhatsApp es: 891-600","number":"584166609161","otp":"891600","panel":"Zone Panel","sender":"WhatsApp","time":"2026-04-16 16:26:43","timestamp":"2026-04-16T16:26:43.995922"}]}