{"success":true,"otps":[{"country":"Venezuela, Bolivarian Republic of","flag":"🇻🇪","id":"2026-04-26 23:40:15_584161827687_&lt;#&gt; Akun WhatsApp Business Anda sedang didaf","masked_number":"58••7687","message":"&lt;#&gt; Akun WhatsApp Business Anda sedang didaftarkan di perangkat baru\\n\\nJangan bagikan kode dengan siapa pun\\nKode WhatsApp Business Anda: 228-593\\nrJbA/XP1K+V","number":"584161827687","otp":"228593","panel":"Zone Panel","sender":"WhatsApp","time":"2026-04-26 23:40:15","timestamp":"2026-04-26T23:40:15.655182"}]}