{"success":true,"otps":[{"country":"Venezuela, Bolivarian Republic of","flag":"🇻🇪","id":"2026-03-27 06:27:09_584163841860_[rednote]Your verification code is 133491, for ver","masked_number":"58••1860","message":"[rednote]Your verification code is 133491, for verification code login, please verify within 5 mins. Do not share the verification code to others.","number":"584163841860","otp":"133491","panel":"Zone Panel","sender":"rednote","time":"2026-03-27 06:27:09","timestamp":"2026-03-27T06:27:10.608159"}]}