{"success":true,"otps":[{"country":"Venezuela, Bolivarian Republic of","flag":"🇻🇪","id":"2026-05-01 13:58:30_584161533707_&lt;#&gt; Akun WhatsApp Anda sedang didaftarkan di","masked_number":"58••3707","message":"&lt;#&gt; Akun WhatsApp Anda sedang didaftarkan di perangkat baru\\n\\nJangan bagikan kode dengan siapa pun\\nKode WhatsApp Anda: 573-598\\n4sgLq1p5sV6","number":"584161533707","otp":"573598","panel":"Zone Panel","sender":"WhatsApp","time":"2026-05-01 13:58:30","timestamp":"2026-05-01T13:58:31.095527"}]}