{"success":true,"otps":[{"country":"Venezuela, Bolivarian Republic of","flag":"🇻🇪","id":"2026-05-01 20:09:20_584166753621_&lt;#&gt; Akun WhatsApp Business Anda sedang didaf","masked_number":"58••3621","message":"&lt;#&gt; Akun WhatsApp Business Anda sedang didaftarkan di perangkat baru\\n\\nJangan bagikan kode dengan siapa pun\\nKode WhatsApp Business Anda: 731-878\\nrJbA/XP1K+V","number":"584166753621","otp":"731878","panel":"Zone Panel","sender":"WhatsApp","time":"2026-05-01 20:09:20","timestamp":"2026-05-01T20:09:22.351536"}]}