{"success":true,"otps":[{"country":"Venezuela, Bolivarian Republic of","flag":"🇻🇪","id":"2026-03-30 21:24:16_584164138773_[rednote]Your verification code is 148537, for ver","masked_number":"58••8773","message":"[rednote]Your verification code is 148537, for verification code login, please verify within 5 mins. Do not share the verification code to others.","number":"584164138773","otp":"148537","panel":"Zone Panel","sender":"rednote","time":"2026-03-30 21:24:16","timestamp":"2026-03-30T21:24:17.583493"}]}