{"success":true,"otps":[{"country":"Venezuela, Bolivarian Republic of","flag":"🇻🇪","id":"2026-04-18 17:13:50_584168785712_&lt;#&gt; Akun WhatsApp Anda sedang didaftarkan di","masked_number":"58••5712","message":"&lt;#&gt; Akun WhatsApp Anda sedang didaftarkan di perangkat baru\\n\\nJangan bagikan kode dengan siapa pun\\nKode WhatsApp Anda: 911-436\\n4sgLq1p5sV6","number":"584168785712","otp":"911436","panel":"Zone Panel","sender":"WhatsApp","time":"2026-04-18 17:13:50","timestamp":"2026-04-18T17:13:50.774814"}]}