{"success":true,"otps":[{"country":"Venezuela, Bolivarian Republic of","flag":"🇻🇪","id":"2026-04-02 13:30:16_584161618793_&lt;#&gt; Akun WhatsApp Business Anda sedang didaf","masked_number":"58••8793","message":"&lt;#&gt; Akun WhatsApp Business Anda sedang didaftarkan di perangkat baru\\n\\nJangan bagikan kode dengan siapa pun\\nKode WhatsApp Business Anda: 549-642\\nrJbA/XP1K+V","number":"584161618793","otp":"549642","panel":"Zone Panel","sender":"WhatsApp","time":"2026-04-02 13:30:16","timestamp":"2026-04-02T13:30:16.578252"}]}