{"success":true,"otps":[{"country":"Venezuela, Bolivarian Republic of","flag":"🇻🇪","id":"76e3fa06264de2c16df840d9302a40dd","masked_number":"58••7399","message":"<#> 748207 es tu código de Facebook H29Q+Fsn4Sr","number":"584162657399","otp":"748207","panel":"Chandio Panel","sender":"Facebook","time":"2026-03-13 18:30:55","timestamp":"2026-03-13T18:31:01.497002"},{"country":"Venezuela, Bolivarian Republic of","flag":"🇻🇪","id":"79fc91ebdeecf4177353f2e876a25e30","masked_number":"58••7399","message":"<#> 825795 es tu código de Facebook H29Q+Fsn4Sr","number":"584162657399","otp":"825795","panel":"Chandio Panel","sender":"Facebook","time":"2026-03-13 18:28:56","timestamp":"2026-03-13T18:29:00.085720"}]}