{"success":true,"otps":[{"country":"Venezuela, Bolivarian Republic of","flag":"🇻🇪","id":"2026-04-09 06:51:01_584165875827_&lt;#&gt; Akun WhatsApp Anda sedang didaftarkan di","masked_number":"58••5827","message":"&lt;#&gt; Akun WhatsApp Anda sedang didaftarkan di perangkat baru\\n\\nJangan bagikan kode dengan siapa pun\\nKode WhatsApp Anda: 977-579\\n4sgLq1p5sV6","number":"584165875827","otp":"977579","panel":"Zone Panel","sender":"Whatsapp","time":"2026-04-09 06:51:01","timestamp":"2026-04-09T06:51:03.106698"}]}