{"success":true,"otps":[{"country":"Venezuela, Bolivarian Republic of","flag":"🇻🇪","id":"d0962a52527e0f02440d9234087ef731","masked_number":"58••7577","message":"<#> Your WhatsApp code: 745-916\nDon't share this code with others\n4sgLq1p5sV6","number":"584163697577","otp":"745916","panel":"Chandio Panel","sender":"WhatsApp","time":"2026-03-14 14:42:33","timestamp":"2026-03-14T14:42:39.823704"},{"country":"Venezuela, Bolivarian Republic of","flag":"🇻🇪","id":"3d97b032e8319f642b83af0b8bafdad6","masked_number":"58••7577","message":"[rednote]Your verification code is 111425, for verification code login, please verify within 5 mins. Do not share the verification code to others.","number":"584163697577","otp":"111425","panel":"Chandio Panel","sender":"RED","time":"2026-03-14 14:36:56","timestamp":"2026-03-14T14:37:02.561796"}]}