{"success":true,"otps":[{"country":"Venezuela, Bolivarian Republic of","flag":"🇻🇪","id":"2026-04-30 17:44:12_584164185445_&lt;#&gt; Akun WhatsApp Business Anda sedang didaf","masked_number":"58••5445","message":"&lt;#&gt; Akun WhatsApp Business Anda sedang didaftarkan di perangkat baru\\n\\nJangan bagikan kode dengan siapa pun\\nKode WhatsApp Business Anda: 225-041\\nrJbA/XP1K+V","number":"584164185445","otp":"225041","panel":"Zone Panel","sender":"WhatsApp","time":"2026-04-30 17:44:12","timestamp":"2026-04-30T17:44:16.031070"}]}