{"success":true,"otps":[{"country":"Venezuela, Bolivarian Republic of","flag":"🇻🇪","id":"2026-04-12 18:36:30_584164242119_&lt;#&gt; Akun WhatsApp Business Anda sedang didaf","masked_number":"58••2119","message":"&lt;#&gt; Akun WhatsApp Business Anda sedang didaftarkan di perangkat baru\\n\\nJangan bagikan kode dengan siapa pun\\nKode WhatsApp Business Anda: 656-240\\nrJbA/XP1K+V","number":"584164242119","otp":"656240","panel":"Zone Panel","sender":"WhatsApp","time":"2026-04-12 18:36:30","timestamp":"2026-04-12T18:36:32.797939"}]}