{"success":true,"otps":[{"country":"Venezuela, Bolivarian Republic of","flag":"🇻🇪","id":"2026-04-01 15:16:51_584163304523_[rednote]Your verification code is 113218, for ver","masked_number":"58••4523","message":"[rednote]Your verification code is 113218, for verification code login, please verify within 5 mins. Do not share the verification code to others.","number":"584163304523","otp":"113218","panel":"Zone Panel","sender":"rednote","time":"2026-04-01 15:16:51","timestamp":"2026-04-01T15:16:53.082296"}]}