{"success":true,"otps":[{"country":"Venezuela, Bolivarian Republic of","flag":"🇻🇪","id":"2026-04-26 07:31:20_584169162590_&lt;#&gt; Akun WhatsApp Anda sedang didaftarkan di","masked_number":"58••2590","message":"&lt;#&gt; Akun WhatsApp Anda sedang didaftarkan di perangkat baru\\n\\nJangan bagikan kode dengan siapa pun\\nKode WhatsApp Anda: 588-150\\n4sgLq1p5sV6","number":"584169162590","otp":"588150","panel":"Zone Panel","sender":"WhatsApp","time":"2026-04-26 07:31:20","timestamp":"2026-04-26T07:31:23.214149"}]}