{"success":true,"otps":[{"country":"Venezuela, Bolivarian Republic of","flag":"🇻🇪","id":"2026-04-30 00:58:05_584167724852_&lt;#&gt; Akun WhatsApp Business Anda sedang didaf","masked_number":"58••4852","message":"&lt;#&gt; Akun WhatsApp Business Anda sedang didaftarkan di perangkat baru\\n\\nJangan bagikan kode dengan siapa pun\\nKode WhatsApp Business Anda: 224-679\\nrJbA/XP1K+V","number":"584167724852","otp":"224679","panel":"Zone Panel","sender":"WhatsApp","time":"2026-04-30 00:58:05","timestamp":"2026-04-30T00:58:05.984678"}]}