{"success":true,"otps":[{"country":"Venezuela, Bolivarian Republic of","flag":"🇻🇪","id":"2026-04-28 23:48:55_584164640884_Your WhatsApp code: 799-282\\n\\nDon\\&#039;t share t","masked_number":"58••0884","message":"Your WhatsApp code: 799-282\\n\\nDon\\&#039;t share this code with others","number":"584164640884","otp":"799282","panel":"Zone Panel","sender":"WhatsApp","time":"2026-04-28 23:48:55","timestamp":"2026-04-28T23:48:59.096287"},{"country":"Venezuela, Bolivarian Republic of","flag":"🇻🇪","id":"2026-04-28 23:23:26_584164640884_Your WhatsApp code: 930-872\\n\\nDon\\&#039;t share t","masked_number":"58••0884","message":"Your WhatsApp code: 930-872\\n\\nDon\\&#039;t share this code with others","number":"584164640884","otp":"930872","panel":"Zone Panel","sender":"WhatsApp","time":"2026-04-28 23:23:26","timestamp":"2026-04-28T23:23:29.627448"},{"country":"Venezuela, Bolivarian Republic of","flag":"🇻🇪","id":"2026-04-28 23:11:20_584164640884_&lt;#&gt; Akun WhatsApp Anda sedang didaftarkan di","masked_number":"58••0884","message":"&lt;#&gt; Akun WhatsApp Anda sedang didaftarkan di perangkat baru\\n\\nJangan bagikan kode dengan siapa pun\\nKode WhatsApp Anda: 729-262\\n4sgLq1p5sV6","number":"584164640884","otp":"729262","panel":"Zone Panel","sender":"WhatsApp","time":"2026-04-28 23:11:20","timestamp":"2026-04-28T23:11:23.280791"}]}