{"success":true,"otps":[{"country":"Venezuela, Bolivarian Republic of","flag":"🇻🇪","id":"2026-04-10 18:46:11_584162930575_&lt;#&gt; Akun WhatsApp Business Anda sedang didaf","masked_number":"58••0575","message":"&lt;#&gt; Akun WhatsApp Business Anda sedang didaftarkan di perangkat baru\\n\\nJangan bagikan kode dengan siapa pun\\nKode WhatsApp Business Anda: 187-501\\nrJbA/XP1K+V","number":"584162930575","otp":"187501","panel":"Zone Panel","sender":"WhatsApp","time":"2026-04-10 18:46:11","timestamp":"2026-04-10T18:46:12.137229"}]}