{"success":true,"otps":[{"country":"Venezuela, Bolivarian Republic of","flag":"🇻🇪","id":"2026-03-28 18:23:30_584164732565_&lt;#&gt; Akun WhatsApp Anda sedang didaftarkan di","masked_number":"58••2565","message":"&lt;#&gt; Akun WhatsApp Anda sedang didaftarkan di perangkat baru\\n\\nJangan bagikan kode dengan siapa pun\\nKode WhatsApp Anda: 125-688\\n4sgLq1p5sV6","number":"584164732565","otp":"125688","panel":"Zone Panel","sender":"Whatsapp","time":"2026-03-28 18:23:30","timestamp":"2026-03-28T18:23:32.206354"}]}