{"success":true,"otps":[{"country":"Venezuela, Bolivarian Republic of","flag":"🇻🇪","id":"2026-05-31 17:35:35_584167756722_&lt;#&gt; Tu cuenta de WhatsApp esta siendo regist","masked_number":"58••6722","message":"&lt;#&gt; Tu cuenta de WhatsApp esta siendo registrada en un dispositivo nuevo\\n\\nNo compartas el codigo con nadie\\nTu codigo de WhatsApp es: 928-816\\n4sgLq1p5sV6","number":"584167756722","otp":"928816","panel":"Zone Panel","sender":"13479471974","time":"2026-05-31 17:35:35","timestamp":"2026-05-31T17:35:37.157234"}]}