{"success":true,"otps":[{"country":"Venezuela, Bolivarian Republic of","flag":"🇻🇪","id":"506fc6dda6baaf5a15410d97dcdc0705","masked_number":"58••0558","message":"[rednote]Your verification code is 155063, for verification code login, please verify within 5 mins. Do not share the verification code to others.","number":"584261210558","otp":"155063","panel":"Chandio Panel","sender":"RED","time":"2026-03-07 19:35:39","timestamp":"2026-03-07T19:35:42.008016"},{"country":"Venezuela, Bolivarian Republic of","flag":"🇻🇪","id":"c3c59b9fa49898b971a6a5a1e8f58a20","masked_number":"58••0558","message":"[rednote]Your verification code is 155063, for verification code login, please verify within 5 mins. Do not share the verification code to others.","number":"584261210558","otp":"155063","panel":"Chandio Panel","sender":"RED","time":"2026-03-07 19:33:32","timestamp":"2026-03-07T19:33:36.169453"}]}