{"success":true,"otps":[{"country":"Venezuela, Bolivarian Republic of","flag":"🇻🇪","id":"2026-04-17 23:25:58_584262939324_&lt;#&gt; Your WhatsApp Business account is being ","masked_number":"58••9324","message":"&lt;#&gt; Your WhatsApp Business account is being registered on a new device\\n\\nDo not share this code with anyone\\nYour WhatsApp Business code: 455-577\\nrJbA/XP1K+V","number":"584262939324","otp":"455577","panel":"Zone Panel","sender":"WhatsApp","time":"2026-04-17 23:25:58","timestamp":"2026-04-17T23:26:01.052834"}]}