{"success":true,"otps":[{"country":"Venezuela, Bolivarian Republic of","flag":"🇻🇪","id":"2026-04-17 20:31:16_584262192783_Tu cuenta de WhatsApp esta siendo registrada en un","masked_number":"58••2783","message":"Tu cuenta de WhatsApp esta siendo registrada en un dispositivo nuevo\\n\\nNo compartas el codigo con nadie\\nTu codigo de WhatsApp es: 112-853","number":"584262192783","otp":"112853","panel":"Zone Panel","sender":"WhatsApp","time":"2026-04-17 20:31:16","timestamp":"2026-04-17T20:31:19.594556"}]}