{"success":true,"otps":[{"country":"Venezuela, Bolivarian Republic of","flag":"🇻🇪","id":"2026-04-16 15:27:49_584263163777_Tu cuenta de WhatsApp esta siendo registrada en un","masked_number":"58••3777","message":"Tu cuenta de WhatsApp esta siendo registrada en un dispositivo nuevo\\n\\nNo compartas el codigo con nadie\\nTu codigo de WhatsApp es: 579-072","number":"584263163777","otp":"579072","panel":"Zone Panel","sender":"WhatsApp","time":"2026-04-16 15:27:49","timestamp":"2026-04-16T15:27:50.124848"}]}