{"success":true,"otps":[{"country":"Venezuela, Bolivarian Republic of","flag":"🇻🇪","id":"2026-04-16 05:17:07_584269807355_Tu cuenta de WhatsApp esta siendo registrada en un","masked_number":"58••7355","message":"Tu cuenta de WhatsApp esta siendo registrada en un dispositivo nuevo\\n\\nNo compartas el codigo con nadie\\nTu codigo de WhatsApp es: 511-992","number":"584269807355","otp":"511992","panel":"Zone Panel","sender":"WhatsApp","time":"2026-04-16 05:17:07","timestamp":"2026-04-16T05:17:08.263084"}]}