{"success":true,"otps":[{"country":"Venezuela, Bolivarian Republic of","flag":"🇻🇪","id":"2026-04-14 09:25:44_584265479415_[rednote] Your verification code is 166341 (for lo","masked_number":"58••9415","message":"[rednote] Your verification code is 166341 (for login via phone number), valid for 5 mins. Do not share it with anyone.","number":"584265479415","otp":"166341","panel":"Zone Panel","sender":"rednote","time":"2026-04-14 09:25:44","timestamp":"2026-04-14T09:25:44.869217"},{"country":"Venezuela, Bolivarian Republic of","flag":"🇻🇪","id":"2026-04-14 09:22:57_584265479415_[rednote] Your verification code is 166341 (for lo","masked_number":"58••9415","message":"[rednote] Your verification code is 166341 (for login via phone number), valid for 5 mins. Do not share it with anyone.","number":"584265479415","otp":"166341","panel":"Zone Panel","sender":"baidu","time":"2026-04-14 09:22:57","timestamp":"2026-04-14T09:22:58.123565"}]}