{"success":true,"otps":[{"country":"Venezuela, Bolivarian Republic of","flag":"🇻🇪","id":"2026-04-03 20:14:28_584264087887_&lt;#&gt; Your WhatsApp Business account is being ","masked_number":"58••7887","message":"&lt;#&gt; Your WhatsApp Business account is being registered on a new device\\n\\nDo not share this code with anyone\\nYour WhatsApp Business code: 107-761\\nrJbA/XP1K+V","number":"584264087887","otp":"107761","panel":"Zone Panel","sender":"Whatsapp","time":"2026-04-03 20:14:28","timestamp":"2026-04-03T20:14:31.063402"}]}