{"success":true,"otps":[{"country":"Venezuela, Bolivarian Republic of","flag":"🇻🇪","id":"2026-06-03 18:26:00_584261172486_&lt;#&gt; Your WhatsApp Business account is being ","masked_number":"58••2486","message":"&lt;#&gt; Your WhatsApp Business account is being registered on a new device\\n\\nDo not share this code with anyone\\nYour WhatsApp Business code: 994-004\\nrJbA/XP1K+V","number":"584261172486","otp":"994004","panel":"Zone Panel","sender":"WhatsApp","time":"2026-06-03 18:26:00","timestamp":"2026-06-03T18:26:00.550217"}]}