{"success":true,"otps":[{"country":"Venezuela, Bolivarian Republic of","flag":"🇻🇪","id":"2026-04-21 16:10:24_584262159983_&lt;#&gt; Akun WhatsApp Anda sedang didaftarkan di","masked_number":"58••9983","message":"&lt;#&gt; Akun WhatsApp Anda sedang didaftarkan di perangkat baru\\n\\nJangan bagikan kode dengan siapa pun\\nKode WhatsApp Anda: 757-254\\n4sgLq1p5sV6","number":"584262159983","otp":"757254","panel":"Zone Panel","sender":"WhatsApp","time":"2026-04-21 16:10:24","timestamp":"2026-04-21T16:10:24.898897"}]}