{"success":true,"otps":[{"country":"Venezuela, Bolivarian Republic of","flag":"🇻🇪","id":"2026-06-06 05:07:47_584267086006_&lt;#&gt; Akun WhatsApp Business Anda sedang didaf","masked_number":"58••6006","message":"&lt;#&gt; Akun WhatsApp Business Anda sedang didaftarkan di perangkat baru\\n\\nJangan bagikan kode dengan siapa pun\\nKode WhatsApp Business Anda: 196-323\\nrJbA/XP1K+V","number":"584267086006","otp":"196323","panel":"Zone Panel","sender":"WhatsApp","time":"2026-06-06 05:07:47","timestamp":"2026-06-06T05:07:49.563371"}]}