{"success":true,"otps":[{"country":"Venezuela, Bolivarian Republic of","flag":"🇻🇪","id":"1812cbb1c621c73b1fd76f64df5a49c8","masked_number":"58••4098","message":"<#> Codigo de WhatsApp Business: 574-576\nNo compartas este codigo con nadie\nrJbA/XP1K+V","number":"584268964098","otp":"574576","panel":"Chandio Panel","sender":"Whatsapp","time":"2026-03-09 22:33:17","timestamp":"2026-03-09T22:33:23.503878"},{"country":"Venezuela, Bolivarian Republic of","flag":"🇻🇪","id":"d3ad2b473972349f0a5804ce2651aff7","masked_number":"58••4098","message":"<#> Codigo de WhatsApp Business: 576-913\nNo compartas este codigo con nadie\nrJbA/XP1K+V","number":"584268964098","otp":"576913","panel":"Chandio Panel","sender":"Whatsapp","time":"2026-03-09 22:32:43","timestamp":"2026-03-09T22:32:50.217057"}]}