{"success":true,"otps":[{"country":"Venezuela, Bolivarian Republic of","flag":"🇻🇪","id":"2026-04-30 22:31:19_584269017327_Akun WhatsApp Business Anda sedang didaftarkan di ","masked_number":"58••7327","message":"Akun WhatsApp Business Anda sedang didaftarkan di perangkat baru\\n\\nJangan bagikan kode dengan siapa pun\\nKode WhatsApp Business Anda: 605-112","number":"584269017327","otp":"605112","panel":"Zone Panel","sender":"WhatsApp","time":"2026-04-30 22:31:19","timestamp":"2026-04-30T22:31:22.966681"}]}