{"success":true,"otps":[{"country":"Venezuela, Bolivarian Republic of","flag":"🇻🇪","id":"2026-06-16 22:08:16_584262192388_PayPal: 728926 is your security code. Don\\&#039;t ","masked_number":"58••2388","message":"PayPal: 728926 is your security code. Don\\&#039;t share your code.","number":"584262192388","otp":"728926","panel":"Zone Panel","sender":"PayPal","time":"2026-06-16 22:08:16","timestamp":"2026-06-16T22:08:17.922219"},{"country":"Venezuela, Bolivarian Republic of","flag":"🇻🇪","id":"2026-06-16 22:08:17_584262192388_PayPal: 259182 is your security code. Don\\&#039;t ","masked_number":"58••2388","message":"PayPal: 259182 is your security code. Don\\&#039;t share your code.","number":"584262192388","otp":"259182","panel":"Zone Panel","sender":"PayPal","time":"2026-06-16 22:08:17","timestamp":"2026-06-16T22:08:17.921847"},{"country":"Venezuela, Bolivarian Republic of","flag":"🇻🇪","id":"2026-06-16 22:08:17_584262192388_PayPal: 106421 is your security code. Don\\&#039;t ","masked_number":"58••2388","message":"PayPal: 106421 is your security code. Don\\&#039;t share your code.","number":"584262192388","otp":"106421","panel":"Zone Panel","sender":"PayPal","time":"2026-06-16 22:08:17","timestamp":"2026-06-16T22:08:17.921492"}]}