{"success":true,"otps":[{"country":"Venezuela, Bolivarian Republic of","flag":"🇻🇪","id":"2026-05-27 16:46:08_584261856107_&lt;#&gt; Akun WhatsApp Anda sedang didaftarkan di","masked_number":"58••6107","message":"&lt;#&gt; Akun WhatsApp Anda sedang didaftarkan di perangkat baru\\n\\nJangan bagikan kode dengan siapa pun\\nKode WhatsApp Anda: 844-572\\n4sgLq1p5sV6","number":"584261856107","otp":"844572","panel":"Zone Panel","sender":"15612993479","time":"2026-05-27 16:46:08","timestamp":"2026-05-27T16:46:10.561001"}]}