{"success":true,"otps":[{"country":"Venezuela, Bolivarian Republic of","flag":"🇻🇪","id":"2026-04-25 17:42:18_584263696533_Akun WhatsApp Business Anda sedang didaftarkan di ","masked_number":"58••6533","message":"Akun WhatsApp Business Anda sedang didaftarkan di perangkat baru\\n\\nJangan bagikan kode dengan siapa pun\\nKode WhatsApp Business Anda: 565-832","number":"584263696533","otp":"565832","panel":"Zone Panel","sender":"WhatsApp","time":"2026-04-25 17:42:18","timestamp":"2026-04-25T17:42:20.517697"}]}