{"success":true,"otps":[{"country":"Venezuela, Bolivarian Republic of","flag":"🇻🇪","id":"2026-05-01 23:59:44_584262529236_&lt;#&gt; Akun WhatsApp Business Anda sedang didaf","masked_number":"58••9236","message":"&lt;#&gt; Akun WhatsApp Business Anda sedang didaftarkan di perangkat baru\\n\\nJangan bagikan kode dengan siapa pun\\nKode WhatsApp Business Anda: 792-410\\nrJbA/XP1K+V","number":"584262529236","otp":"792410","panel":"Zone Panel","sender":"WhatsApp","time":"2026-05-01 23:59:44","timestamp":"2026-05-01T23:59:45.622479"}]}