{"success":true,"otps":[{"country":"Venezuela, Bolivarian Republic of","flag":"🇻🇪","id":"2026-04-04 20:55:23_584267904719_&lt;#&gt; Akun WhatsApp Business Anda sedang didaf","masked_number":"58••4719","message":"&lt;#&gt; Akun WhatsApp Business Anda sedang didaftarkan di perangkat baru\\n\\nJangan bagikan kode dengan siapa pun\\nKode WhatsApp Business Anda: 393-202\\nrJbA/XP1K+V","number":"584267904719","otp":"393202","panel":"Zone Panel","sender":"Whatsapp","time":"2026-04-04 20:55:23","timestamp":"2026-04-04T20:55:24.236451"}]}