{"success":true,"otps":[{"country":"Venezuela, Bolivarian Republic of","flag":"🇻🇪","id":"2026-04-26 21:44:54_584263799599_&lt;#&gt; Your WhatsApp Business account is being ","masked_number":"58••9599","message":"&lt;#&gt; Your WhatsApp Business account is being registered on a new device\\n\\nDo not share this code with anyone\\nYour WhatsApp Business code: 346-925\\nrJbA/XP1K+V","number":"584263799599","otp":"346925","panel":"Zone Panel","sender":"WhatsApp","time":"2026-04-26 21:44:54","timestamp":"2026-04-26T21:44:56.597089"}]}