{"success":true,"otps":[{"country":"Venezuela, Bolivarian Republic of","flag":"🇻🇪","id":"2026-05-03 14:16:42_584269679216_&lt;#&gt; Tu cuenta de WhatsApp esta siendo regist","masked_number":"58••9216","message":"&lt;#&gt; Tu cuenta de WhatsApp esta siendo registrada en un dispositivo nuevo\\n\\nNo compartas el codigo con nadie\\nTu codigo de WhatsApp es: 400-157\\n4sgLq1p5sV6","number":"584269679216","otp":"400157","panel":"Zone Panel","sender":"WhatsApp","time":"2026-05-03 14:16:42","timestamp":"2026-05-03T14:16:43.124665"}]}