{"success":true,"otps":[{"country":"Venezuela, Bolivarian Republic of","flag":"🇻🇪","id":"2026-04-28 08:44:03_584265523144_&lt;#&gt; Akun WhatsApp Anda sedang didaftarkan di","masked_number":"58••3144","message":"&lt;#&gt; Akun WhatsApp Anda sedang didaftarkan di perangkat baru\\n\\nJangan bagikan kode dengan siapa pun\\nKode WhatsApp Anda: 293-858\\n4sgLq1p5sV6","number":"584265523144","otp":"293858","panel":"Zone Panel","sender":"17632805379","time":"2026-04-28 08:44:03","timestamp":"2026-04-28T08:44:07.468607"}]}