{"success":true,"otps":[{"country":"Venezuela, Bolivarian Republic of","flag":"🇻🇪","id":"2026-04-19 11:19:18_584262155842_&lt;#&gt; Akun WhatsApp Business Anda sedang didaf","masked_number":"58••5842","message":"&lt;#&gt; Akun WhatsApp Business Anda sedang didaftarkan di perangkat baru\\n\\nJangan bagikan kode dengan siapa pun\\nKode WhatsApp Business Anda: 379-996\\nrJbA/XP1K+V","number":"584262155842","otp":"379996","panel":"Zone Panel","sender":"WhatsApp","time":"2026-04-19 11:19:18","timestamp":"2026-04-19T11:19:22.001963"}]}