{"success":true,"otps":[{"country":"Venezuela, Bolivarian Republic of","flag":"🇻🇪","id":"2026-04-30 14:42:15_584264996895_&lt;#&gt; Akun WhatsApp Business Anda sedang didaf","masked_number":"58••6895","message":"&lt;#&gt; Akun WhatsApp Business Anda sedang didaftarkan di perangkat baru\\n\\nJangan bagikan kode dengan siapa pun\\nKode WhatsApp Business Anda: 762-885\\nrJbA/XP1K+V","number":"584264996895","otp":"762885","panel":"Zone Panel","sender":"WhatsApp","time":"2026-04-30 14:42:15","timestamp":"2026-04-30T14:42:17.894838"}]}