{"success":true,"otps":[{"country":"Venezuela, Bolivarian Republic of","flag":"🇻🇪","id":"2026-04-01 11:49:35_584264692188_&lt;#&gt; Akun WhatsApp Business Anda sedang didaf","masked_number":"58••2188","message":"&lt;#&gt; Akun WhatsApp Business Anda sedang didaftarkan di perangkat baru\\n\\nJangan bagikan kode dengan siapa pun\\nKode WhatsApp Business Anda: 926-851\\nrJbA/XP1K+V","number":"584264692188","otp":"926851","panel":"Zone Panel","sender":"WhatsApp","time":"2026-04-01 11:49:35","timestamp":"2026-04-01T11:49:35.769030"}]}