{"success":true,"otps":[{"country":"Venezuela, Bolivarian Republic of","flag":"🇻🇪","id":"2026-06-03 23:19:17_584269424842_Akun WhatsApp Business Anda sedang didaftarkan di ","masked_number":"58••4842","message":"Akun WhatsApp Business Anda sedang didaftarkan di perangkat baru\\n\\nJangan bagikan kode dengan siapa pun\\nKode WhatsApp Business Anda: 518-052","number":"584269424842","otp":"518052","panel":"Zone Panel","sender":"WhatsApp","time":"2026-06-03 23:19:17","timestamp":"2026-06-03T23:19:20.071874"}]}