{"success":true,"otps":[{"country":"Venezuela, Bolivarian Republic of","flag":"🇻🇪","id":"2026-06-06 17:19:50_584262872858_&lt;#&gt; Akun WhatsApp Anda sedang didaftarkan di","masked_number":"58••2858","message":"&lt;#&gt; Akun WhatsApp Anda sedang didaftarkan di perangkat baru\\n\\nJangan bagikan kode dengan siapa pun\\nKode WhatsApp Anda: 130-828\\n4sgLq1p5sV6","number":"584262872858","otp":"130828","panel":"Zone Panel","sender":"WhatsApp","time":"2026-06-06 17:19:50","timestamp":"2026-06-06T17:19:53.129050"}]}