{"success":true,"otps":[{"country":"Venezuela, Bolivarian Republic of","flag":"🇻🇪","id":"2026-05-03 17:16:42_584262225681_&lt;#&gt; Akun WhatsApp Business Anda sedang didaf","masked_number":"58••5681","message":"&lt;#&gt; Akun WhatsApp Business Anda sedang didaftarkan di perangkat baru\\n\\nJangan bagikan kode dengan siapa pun\\nKode WhatsApp Business Anda: 254-586\\nrJbA/XP1K+V","number":"584262225681","otp":"254586","panel":"Zone Panel","sender":"WhatsApp","time":"2026-05-03 17:16:42","timestamp":"2026-05-03T17:16:43.032306"}]}