{"success":true,"otps":[{"country":"Venezuela, Bolivarian Republic of","flag":"🇻🇪","id":"2026-04-02 17:25:11_584262136444_&lt;#&gt; Akun WhatsApp Business Anda sedang didaf","masked_number":"58••6444","message":"&lt;#&gt; Akun WhatsApp Business Anda sedang didaftarkan di perangkat baru\\n\\nJangan bagikan kode dengan siapa pun\\nKode WhatsApp Business Anda: 903-985\\nrJbA/XP1K+V","number":"584262136444","otp":"903985","panel":"Zone Panel","sender":"Whatsapp","time":"2026-04-02 17:25:11","timestamp":"2026-04-02T17:25:12.301469"}]}