{"success":true,"otps":[{"country":"Venezuela, Bolivarian Republic of","flag":"🇻🇪","id":"303d41bc8c93cdba85fbd7876899abe4","masked_number":"58••0381","message":"<#> Kode WhatsApp Business: 411-078\nJangan bagikan kode ini dengan orang lain\nrJbA/XP1K+V","number":"584262770381","otp":"411078","panel":"Chandio Panel","sender":"SMSInfo","time":"2026-03-10 09:41:15","timestamp":"2026-03-10T09:41:21.943933"},{"country":"Venezuela, Bolivarian Republic of","flag":"🇻🇪","id":"43f5a9d3723cfecf485a6d8846b52492","masked_number":"58••0381","message":"<#> Akun WhatsApp Business Anda sedang didaftarkan di perangkat baru\n\nJangan bagikan kode dengan siapa pun\nKode WhatsApp Business Anda: 779-329\nrJbA/XP1K+V","number":"584262770381","otp":"779329","panel":"Chandio Panel","sender":"WhatsApp","time":"2026-03-10 09:14:31","timestamp":"2026-03-10T09:14:34.432698"}]}