{"success":true,"otps":[{"country":"Venezuela, Bolivarian Republic of","flag":"🇻🇪","id":"453be6b15652a27000fb05454eef9618","masked_number":"58••3654","message":"Your WhatsApp code: 773-329\n\nDon't share this code with others","number":"584269753654","otp":"773329","panel":"Chandio Panel","sender":"Whatsapp","time":"2026-03-21 04:42:34","timestamp":"2026-03-21T04:42:40.445185"},{"country":"Venezuela, Bolivarian Republic of","flag":"🇻🇪","id":"a104ad73b9ea80587f826d5844b83090","masked_number":"58••3654","message":"Your WhatsApp code: 855-983\n\nDon't share this code with others","number":"584269753654","otp":"855983","panel":"Chandio Panel","sender":"Whatsapp","time":"2026-03-21 04:41:54","timestamp":"2026-03-21T04:42:01.578516"}]}