{"success":true,"otps":[{"country":"Venezuela, Bolivarian Republic of","flag":"🇻🇪","id":"2026-04-19 22:35:30_584267235599_Your WhatsApp code: 917-729\\n\\nDon\\&#039;t share t","masked_number":"58••5599","message":"Your WhatsApp code: 917-729\\n\\nDon\\&#039;t share this code with others","number":"584267235599","otp":"917729","panel":"Zone Panel","sender":"WhatsApp","time":"2026-04-19 22:35:30","timestamp":"2026-04-19T22:35:31.012928"},{"country":"Venezuela, Bolivarian Republic of","flag":"🇻🇪","id":"2026-04-19 22:09:19_584267235599_Your WhatsApp code: 808-022\\n\\nDon\\&#039;t share t","masked_number":"58••5599","message":"Your WhatsApp code: 808-022\\n\\nDon\\&#039;t share this code with others","number":"584267235599","otp":"808022","panel":"Zone Panel","sender":"WhatsApp","time":"2026-04-19 22:09:19","timestamp":"2026-04-19T22:09:22.390898"}]}