{"success":true,"otps":[{"country":"Venezuela, Bolivarian Republic of","flag":"🇻🇪","id":"2026-04-08 18:29:52_584262791196_[rednote] Your verification code is 125165 (for lo","masked_number":"58••1196","message":"[rednote] Your verification code is 125165 (for login via phone number), valid for 5 mins. Do not share it with anyone.","number":"584262791196","otp":"125165","panel":"Zone Panel","sender":"rednote","time":"2026-04-08 18:29:52","timestamp":"2026-04-08T18:29:54.434695"},{"country":"Venezuela, Bolivarian Republic of","flag":"🇻🇪","id":"2026-04-08 18:27:53_584262791196_[rednote] Your verification code is 108441 (for lo","masked_number":"58••1196","message":"[rednote] Your verification code is 108441 (for login via phone number), valid for 5 mins. Do not share it with anyone.","number":"584262791196","otp":"108441","panel":"Zone Panel","sender":"rednote","time":"2026-04-08 18:27:53","timestamp":"2026-04-08T18:27:56.480707"}]}