{"success":true,"otps":[{"country":"Russian Federation","flag":"🇷🇺","id":"2026-05-09 19:46:21_79023278888_[rednote] Your verification code is 187139 for log","masked_number":"79••8888","message":"[rednote] Your verification code is 187139 for login via phone number valid for 5 mins Do not share it with anyone","number":"79023278888","otp":"187139","panel":"Maitt Panel","sender":"iATSMS","time":"2026-05-09 19:46:21","timestamp":"2026-05-09T19:46:22.360506"},{"country":"Russian Federation","flag":"🇷🇺","id":"2026-05-09 19:37:45_79023278888_[rednote] Your verification code is 189607 for log","masked_number":"79••8888","message":"[rednote] Your verification code is 189607 for login via phone number valid for 5 mins Do not share it with anyone","number":"79023278888","otp":"189607","panel":"Maitt Panel","sender":"iATSMS","time":"2026-05-09 19:37:45","timestamp":"2026-05-09T19:37:47.423421"}]}