{"success":true,"otps":[{"country":"Russian Federation","flag":"🇷🇺","id":"2026-07-08 06:55:37_79166238174_Dear Customer,For notifications including a custom","masked_number":"79••8174","message":"Dear Customer,For notifications including a customer secret such as a statement to be delivered via SMS, MMS, service should be obtained from operators p","number":"79166238174","otp":null,"panel":"Zone Panel","sender":"BILGIMSJ","time":"2026-07-08 06:55:37","timestamp":"2026-07-08T06:55:39.243495"},{"country":"Russian Federation","flag":"🇷🇺","id":"2026-07-08 06:55:37_79166238174_rating abroad. *Information:08502220800 MERSIS:029","masked_number":"79••8174","message":"rating abroad. *Information:08502220800 MERSIS:0292008449600341 B002","number":"79166238174","otp":null,"panel":"Zone Panel","sender":"BILGIMSJ","time":"2026-07-08 06:55:37","timestamp":"2026-07-08T06:55:39.243080"},{"country":"Russian Federation","flag":"🇷🇺","id":"2026-07-08 06:55:37_79166238174_roviding electronic communication service operatin","masked_number":"79••8174","message":"roviding electronic communication service operating in Turkiye. Notifications cannot be delivered via SMS, MMS as you receive services from operators ope","number":"79166238174","otp":null,"panel":"Zone Panel","sender":"BILGIMSJ","time":"2026-07-08 06:55:37","timestamp":"2026-07-08T06:55:39.242668"}]}