{"success":true,"otps":[{"country":"Russian Federation","flag":"🇷🇺","id":"2026-05-02 07:21:37_79215625308_Your WhatsApp account is being registered on a new","masked_number":"79••5308","message":"Your WhatsApp account is being registered on a new devicennDo not share this code with anyonenYour WhatsApp code 467-474","number":"79215625308","otp":"467474","panel":"Maitt Panel","sender":"WhatsApp","time":"2026-05-02 07:21:37","timestamp":"2026-05-02T07:21:44.969278"},{"country":"Russian Federation","flag":"🇷🇺","id":"2026-05-02 07:20:21_79215625308_Your WhatsApp account is being registered on a new","masked_number":"79••5308","message":"Your WhatsApp account is being registered on a new devicennDo not share this code with anyonenYour WhatsApp code 934-305","number":"79215625308","otp":"934305","panel":"Maitt Panel","sender":"WhatsApp","time":"2026-05-02 07:20:21","timestamp":"2026-05-02T07:20:26.585707"},{"country":"Russian Federation","flag":"🇷🇺","id":"2026-05-02 07:17:17_79215625308_# Kode WhatsApp 816-965nJangan bagikan kode ini de","masked_number":"79••5308","message":"# Kode WhatsApp 816-965nJangan bagikan kode ini dengan orang lainn4sgLq1p5sV6","number":"79215625308","otp":null,"panel":"Maitt Panel","sender":"WhatsApp","time":"2026-05-02 07:17:17","timestamp":"2026-05-02T07:17:20.965299"},{"country":"Russian Federation","flag":"🇷🇺","id":"2026-05-02 06:51:11_79215625308_# Akun WhatsApp Anda sedang didaftarkan di perangk","masked_number":"79••5308","message":"# Akun WhatsApp Anda sedang didaftarkan di perangkat barunnJangan bagikan kode dengan siapa punnKode WhatsApp Anda 932-767n4sgLq1p5sV6","number":"79215625308","otp":null,"panel":"Maitt Panel","sender":"WhatsApp","time":"2026-05-02 06:51:11","timestamp":"2026-05-02T06:51:19.615035"}]}