{"success":true,"otps":[{"country":"Russian Federation","flag":"🇷🇺","id":"2026-07-20 11:45:29_79278138470_&lt;#&gt; Your WhatsApp account is being registere","masked_number":"79••8470","message":"&lt;#&gt; Your WhatsApp account is being registered on a new device\\n\\nDo not share this code with anyone\\nYour WhatsApp code: 354-348\\n4sgLq1p5sV6","number":"79278138470","otp":"354348","panel":"Zone Panel","sender":"WhatsApp","time":"2026-07-20 11:45:29","timestamp":"2026-07-20T11:45:32.419683"}]}