{"success":true,"otps":[{"country":"Russian Federation","flag":"🇷🇺","id":"2026-07-04 16:17:03_79510743152_&lt;#&gt; Akun WhatsApp Business Anda sedang didaf","masked_number":"79••3152","message":"&lt;#&gt; Akun WhatsApp Business Anda sedang didaftarkan di perangkat baru\\n\\nJangan bagikan kode dengan siapa pun\\nKode WhatsApp Business Anda: 684-583\\nrJbA/XP1K+V","number":"79510743152","otp":"684583","panel":"Zone Panel","sender":"WhatsApp","time":"2026-07-04 16:17:03","timestamp":"2026-07-04T16:17:05.104775"}]}