{"success":true,"otps":[{"country":"Russian Federation","flag":"🇷🇺","id":"262fd8195a8f14a8c80eee4e13ee00b0","masked_number":"79••4049","message":"<#> Kode WhatsApp: 714-166\nJangan bagikan kode ini dengan orang lain\n4sgLq1p5sV6","number":"79917094049","otp":"714166","panel":"Chandio Panel","sender":"WhatsApp","time":"2026-05-10 16:32:28","timestamp":"2026-05-10T16:32:33.449676"},{"country":"Russian Federation","flag":"🇷🇺","id":"e3fc0c7539c4e1b6485463c5d66cb900","masked_number":"79••4049","message":"<#> Akun WhatsApp Anda sedang didaftarkan di perangkat baru\n\nJangan bagikan kode dengan siapa pun\nKode WhatsApp Anda: 546-896\n4sgLq1p5sV6","number":"79917094049","otp":"546896","panel":"Chandio Panel","sender":"WhatsApp","time":"2026-05-10 16:06:20","timestamp":"2026-05-10T16:06:30.294396"}]}