{"success":true,"otps":[{"country":"Russian Federation","flag":"🇷🇺","id":"2026-05-05 08:50:20_79961296620_[rednote] Your verification code is 120877 for log","masked_number":"79••6620","message":"[rednote] Your verification code is 120877 for login via phone number valid for 5 mins Do not share it with anyone","number":"79961296620","otp":"120877","panel":"Maitt Panel","sender":"NOTICE","time":"2026-05-05 08:50:20","timestamp":"2026-05-05T08:50:24.221283"},{"country":"Russian Federation","flag":"🇷🇺","id":"2026-05-05 08:49:20_79961296620_[rednote] Your verification code is 120877 for log","masked_number":"79••6620","message":"[rednote] Your verification code is 120877 for login via phone number valid for 5 mins Do not share it with anyone","number":"79961296620","otp":"120877","panel":"Maitt Panel","sender":"NOTICE","time":"2026-05-05 08:49:20","timestamp":"2026-05-05T08:49:24.213865"}]}